rlbot_twitch_broker_server/__init__.py
rlbot_twitch_broker_server/__main__.py
rlbot_twitch_broker_server/chat_buffer.py
rlbot_twitch_broker_server/client_registry.py
rlbot_twitch_broker_server/encoder.py
rlbot_twitch_broker_server/run.py
rlbot_twitch_broker_server/typing_utils.py
rlbot_twitch_broker_server/util.py
rlbot_twitch_broker_server/controllers/__init__.py
rlbot_twitch_broker_server/controllers/authorization_controller.py
rlbot_twitch_broker_server/controllers/chat_controller.py
rlbot_twitch_broker_server/controllers/register_controller.py
rlbot_twitch_broker_server/controllers/static_controller.py
rlbot_twitch_broker_server/models/__init__.py
rlbot_twitch_broker_server/models/action_server_registration.py
rlbot_twitch_broker_server/models/api_response.py
rlbot_twitch_broker_server/models/base_model_.py
rlbot_twitch_broker_server/models/chat_line.py
rlbot_twitch_broker_server/swagger/swagger.yaml
rlbot_twitch_broker_server/test/__init__.py
rlbot_twitch_broker_server/test/test_chat_controller.py
rlbot_twitch_broker_server/test/test_register_controller.py
rlbot_twitch_broker_server/test/test_static_controller.py
rlbot_twitch_broker_server-1.0.0.dist-info/METADATA
rlbot_twitch_broker_server-1.0.0.dist-info/WHEEL
rlbot_twitch_broker_server-1.0.0.dist-info/entry_points.txt
rlbot_twitch_broker_server-1.0.0.dist-info/top_level.txt
rlbot_twitch_broker_server-1.0.0.dist-info/RECORD
